{
    "url": "https://finder.porsche.com/de/de-DE/search",
    "consumedPdsVersionsWithPrefixes": {
        "2.19.0": [
            "fnssr",
            "fn"
        ]
    },
    "aggregatedConsumedTagNames": {
        "tagNames": {
            "p-marque": {
                "amount": 1,
                "hostPdsComponent": null,
                "children": null,
                "properties": {
                    "trademark": {
                        "amount": 1,
                        "values": {
                            "true": 1
                        }
                    },
                    "size": {
                        "amount": 1,
                        "values": {
                            "responsive": 1
                        }
                    },
                    "target": {
                        "amount": 1,
                        "values": {
                            "_self": 1
                        }
                    }
                },
                "unusedProperties": [
                    "href",
                    "aria"
                ]
            },
            "p-icon": {
                "amount": 60,
                "hostPdsComponent": 17,
                "children": null,
                "properties": {
                    "name": {
                        "amount": 60,
                        "values": {
                            "arrow-head-right": 16,
                            "bookmark": 16,
                            "user": 1,
                            "adjust": 1,
                            "minus": 2,
                            "arrow-head-down": 2,
                            "check": 2,
                            "plus": 16,
                            "sort": 1,
                            "arrow-left": 1,
                            "arrow-right": 1,
                            "information": 1
                        }
                    },
                    "source": {
                        "amount": 1,
                        "values": {
                            "/assets/icons/search-agent.svg": 1
                        }
                    },
                    "color": {
                        "amount": 60,
                        "values": {
                            "inherit": 60
                        }
                    },
                    "size": {
                        "amount": 60,
                        "values": {
                            "small": 45,
                            "inherit": 15
                        }
                    },
                    "lazy": {
                        "amount": 60,
                        "values": {
                            "false": 60
                        }
                    },
                    "theme": {
                        "amount": 60,
                        "values": {
                            "light": 45,
                            "dark": 15
                        }
                    }
                },
                "unusedProperties": [
                    "aria"
                ]
            },
            "p-checkbox-wrapper": {
                "amount": 4,
                "hostPdsComponent": null,
                "children": 4,
                "properties": {
                    "label": {
                        "amount": 4,
                        "values": {
                            "": 4
                        }
                    },
                    "state": {
                        "amount": 4,
                        "values": {
                            "none": 4
                        }
                    },
                    "message": {
                        "amount": 4,
                        "values": {
                            "": 4
                        }
                    },
                    "hideLabel": {
                        "amount": 4,
                        "values": {
                            "false": 4
                        }
                    }
                },
                "unusedProperties": []
            },
            "p-select-wrapper": {
                "amount": 2,
                "hostPdsComponent": null,
                "children": 2,
                "properties": {
                    "label": {
                        "amount": 2,
                        "values": {
                            "Modelle": 1,
                            "": 1
                        }
                    },
                    "description": {
                        "amount": 2,
                        "values": {
                            "": 2
                        }
                    },
                    "state": {
                        "amount": 2,
                        "values": {
                            "none": 2
                        }
                    },
                    "message": {
                        "amount": 2,
                        "values": {
                            "": 2
                        }
                    },
                    "hideLabel": {
                        "amount": 2,
                        "values": {
                            "true": 2
                        }
                    },
                    "filter": {
                        "amount": 2,
                        "values": {
                            "false": 2
                        }
                    },
                    "theme": {
                        "amount": 2,
                        "values": {
                            "light": 2
                        }
                    },
                    "dropdownDirection": {
                        "amount": 2,
                        "values": {
                            "auto": 2
                        }
                    },
                    "native": {
                        "amount": 2,
                        "values": {
                            "false": 2
                        }
                    }
                },
                "unusedProperties": []
            },
            "p-toast": {
                "amount": 1,
                "hostPdsComponent": null,
                "children": null,
                "properties": {
                    "theme": {
                        "amount": 1,
                        "values": {
                            "light": 1
                        }
                    }
                },
                "unusedProperties": []
            },
            "p-tag": {
                "amount": 15,
                "hostPdsComponent": null,
                "children": 15,
                "properties": {
                    "theme": {
                        "amount": 15,
                        "values": {
                            "light": 15
                        }
                    },
                    "color": {
                        "amount": 15,
                        "values": {
                            "neutral-contrast-high": 15
                        }
                    }
                },
                "unusedProperties": [
                    "icon",
                    "iconSource"
                ]
            },
            "p-link": {
                "amount": 15,
                "hostPdsComponent": null,
                "children": 15,
                "properties": {
                    "variant": {
                        "amount": 15,
                        "values": {
                            "secondary": 15
                        }
                    },
                    "icon": {
                        "amount": 15,
                        "values": {
                            "arrow-head-right": 15
                        }
                    },
                    "theme": {
                        "amount": 15,
                        "values": {
                            "light": 15
                        }
                    },
                    "target": {
                        "amount": 15,
                        "values": {
                            "_self": 15
                        }
                    },
                    "hideLabel": {
                        "amount": 15,
                        "values": {
                            "false": 15
                        }
                    }
                },
                "unusedProperties": [
                    "iconSource",
                    "href",
                    "download",
                    "rel",
                    "aria"
                ]
            },
            "p-text": {
                "amount": 4,
                "hostPdsComponent": null,
                "children": 4,
                "properties": {
                    "tag": {
                        "amount": 4,
                        "values": {
                            "p": 4
                        }
                    },
                    "size": {
                        "amount": 4,
                        "values": {
                            "small": 4
                        }
                    },
                    "weight": {
                        "amount": 4,
                        "values": {
                            "regular": 4
                        }
                    },
                    "align": {
                        "amount": 4,
                        "values": {
                            "left": 4
                        }
                    },
                    "color": {
                        "amount": 4,
                        "values": {
                            "default": 1,
                            "inherit": 3
                        }
                    },
                    "ellipsis": {
                        "amount": 4,
                        "values": {
                            "false": 4
                        }
                    },
                    "theme": {
                        "amount": 4,
                        "values": {
                            "light": 4
                        }
                    }
                },
                "unusedProperties": []
            },
            "p-flex": {
                "amount": 1,
                "hostPdsComponent": null,
                "children": 1,
                "properties": {
                    "inline": {
                        "amount": 1,
                        "values": {
                            "false": 1
                        }
                    },
                    "wrap": {
                        "amount": 1,
                        "values": {
                            "nowrap": 1
                        }
                    },
                    "direction": {
                        "amount": 1,
                        "values": {
                            "row": 1
                        }
                    },
                    "justifyContent": {
                        "amount": 1,
                        "values": {
                            "flex-start": 1
                        }
                    },
                    "alignItems": {
                        "amount": 1,
                        "values": {
                            "center": 1
                        }
                    },
                    "alignContent": {
                        "amount": 1,
                        "values": {
                            "stretch": 1
                        }
                    }
                },
                "unusedProperties": []
            }
        },
        "unusedTagNames": [
            "p-accordion",
            "p-banner",
            "p-button",
            "p-button-group",
            "p-button-pure",
            "p-carousel",
            "p-content-wrapper",
            "p-divider",
            "p-fieldset-wrapper",
            "p-flex-item",
            "p-grid",
            "p-grid-item",
            "p-headline",
            "p-inline-notification",
            "p-link-pure",
            "p-link-social",
            "p-link-tile",
            "p-modal",
            "p-pagination",
            "p-popover",
            "p-radio-button-wrapper",
            "p-scroller",
            "p-segmented-control",
            "p-segmented-control-item",
            "p-spinner",
            "p-stepper-horizontal",
            "p-stepper-horizontal-item",
            "p-switch",
            "p-table",
            "p-table-body",
            "p-table-cell",
            "p-table-head",
            "p-table-head-cell",
            "p-table-head-row",
            "p-table-row",
            "p-tabs",
            "p-tabs-bar",
            "p-tabs-item",
            "p-tag-dismissible",
            "p-text-field-wrapper",
            "p-text-list",
            "p-text-list-item",
            "p-textarea-wrapper"
        ]
    },
    "aggregatedConsumedTagNamesForVersionsAndPrefixes": {
        "2.19.0": {
            "fnssr": {
                "tagNames": {
                    "p-marque": {
                        "amount": 1,
                        "hostPdsComponent": null,
                        "children": null,
                        "properties": {
                            "trademark": {
                                "amount": 1,
                                "values": {
                                    "true": 1
                                }
                            },
                            "size": {
                                "amount": 1,
                                "values": {
                                    "responsive": 1
                                }
                            },
                            "target": {
                                "amount": 1,
                                "values": {
                                    "_self": 1
                                }
                            }
                        },
                        "unusedProperties": [
                            "href",
                            "aria"
                        ]
                    },
                    "p-icon": {
                        "amount": 59,
                        "hostPdsComponent": 17,
                        "children": null,
                        "properties": {
                            "name": {
                                "amount": 59,
                                "values": {
                                    "arrow-head-right": 16,
                                    "bookmark": 16,
                                    "user": 1,
                                    "adjust": 1,
                                    "minus": 2,
                                    "arrow-head-down": 2,
                                    "check": 2,
                                    "plus": 16,
                                    "sort": 1,
                                    "arrow-left": 1,
                                    "arrow-right": 1
                                }
                            },
                            "source": {
                                "amount": 1,
                                "values": {
                                    "/assets/icons/search-agent.svg": 1
                                }
                            },
                            "color": {
                                "amount": 59,
                                "values": {
                                    "inherit": 59
                                }
                            },
                            "size": {
                                "amount": 59,
                                "values": {
                                    "small": 44,
                                    "inherit": 15
                                }
                            },
                            "lazy": {
                                "amount": 59,
                                "values": {
                                    "false": 59
                                }
                            },
                            "theme": {
                                "amount": 59,
                                "values": {
                                    "light": 44,
                                    "dark": 15
                                }
                            }
                        },
                        "unusedProperties": [
                            "aria"
                        ]
                    },
                    "p-checkbox-wrapper": {
                        "amount": 4,
                        "hostPdsComponent": null,
                        "children": 4,
                        "properties": {
                            "label": {
                                "amount": 4,
                                "values": {
                                    "": 4
                                }
                            },
                            "state": {
                                "amount": 4,
                                "values": {
                                    "none": 4
                                }
                            },
                            "message": {
                                "amount": 4,
                                "values": {
                                    "": 4
                                }
                            },
                            "hideLabel": {
                                "amount": 4,
                                "values": {
                                    "false": 4
                                }
                            }
                        },
                        "unusedProperties": []
                    },
                    "p-select-wrapper": {
                        "amount": 2,
                        "hostPdsComponent": null,
                        "children": 2,
                        "properties": {
                            "label": {
                                "amount": 2,
                                "values": {
                                    "Modelle": 1,
                                    "": 1
                                }
                            },
                            "description": {
                                "amount": 2,
                                "values": {
                                    "": 2
                                }
                            },
                            "state": {
                                "amount": 2,
                                "values": {
                                    "none": 2
                                }
                            },
                            "message": {
                                "amount": 2,
                                "values": {
                                    "": 2
                                }
                            },
                            "hideLabel": {
                                "amount": 2,
                                "values": {
                                    "true": 2
                                }
                            },
                            "filter": {
                                "amount": 2,
                                "values": {
                                    "false": 2
                                }
                            },
                            "theme": {
                                "amount": 2,
                                "values": {
                                    "light": 2
                                }
                            },
                            "dropdownDirection": {
                                "amount": 2,
                                "values": {
                                    "auto": 2
                                }
                            },
                            "native": {
                                "amount": 2,
                                "values": {
                                    "false": 2
                                }
                            }
                        },
                        "unusedProperties": []
                    },
                    "p-toast": {
                        "amount": 1,
                        "hostPdsComponent": null,
                        "children": null,
                        "properties": {
                            "theme": {
                                "amount": 1,
                                "values": {
                                    "light": 1
                                }
                            }
                        },
                        "unusedProperties": []
                    },
                    "p-tag": {
                        "amount": 15,
                        "hostPdsComponent": null,
                        "children": 15,
                        "properties": {
                            "theme": {
                                "amount": 15,
                                "values": {
                                    "light": 15
                                }
                            },
                            "color": {
                                "amount": 15,
                                "values": {
                                    "neutral-contrast-high": 15
                                }
                            }
                        },
                        "unusedProperties": [
                            "icon",
                            "iconSource"
                        ]
                    },
                    "p-link": {
                        "amount": 15,
                        "hostPdsComponent": null,
                        "children": 15,
                        "properties": {
                            "variant": {
                                "amount": 15,
                                "values": {
                                    "secondary": 15
                                }
                            },
                            "icon": {
                                "amount": 15,
                                "values": {
                                    "arrow-head-right": 15
                                }
                            },
                            "theme": {
                                "amount": 15,
                                "values": {
                                    "light": 15
                                }
                            },
                            "target": {
                                "amount": 15,
                                "values": {
                                    "_self": 15
                                }
                            },
                            "hideLabel": {
                                "amount": 15,
                                "values": {
                                    "false": 15
                                }
                            }
                        },
                        "unusedProperties": [
                            "iconSource",
                            "href",
                            "download",
                            "rel",
                            "aria"
                        ]
                    }
                },
                "unusedTagNames": [
                    "p-accordion",
                    "p-banner",
                    "p-button",
                    "p-button-group",
                    "p-button-pure",
                    "p-carousel",
                    "p-content-wrapper",
                    "p-divider",
                    "p-fieldset-wrapper",
                    "p-flex",
                    "p-flex-item",
                    "p-grid",
                    "p-grid-item",
                    "p-headline",
                    "p-inline-notification",
                    "p-link-pure",
                    "p-link-social",
                    "p-link-tile",
                    "p-modal",
                    "p-pagination",
                    "p-popover",
                    "p-radio-button-wrapper",
                    "p-scroller",
                    "p-segmented-control",
                    "p-segmented-control-item",
                    "p-spinner",
                    "p-stepper-horizontal",
                    "p-stepper-horizontal-item",
                    "p-switch",
                    "p-table",
                    "p-table-body",
                    "p-table-cell",
                    "p-table-head",
                    "p-table-head-cell",
                    "p-table-head-row",
                    "p-table-row",
                    "p-tabs",
                    "p-tabs-bar",
                    "p-tabs-item",
                    "p-tag-dismissible",
                    "p-text",
                    "p-text-field-wrapper",
                    "p-text-list",
                    "p-text-list-item",
                    "p-textarea-wrapper"
                ]
            },
            "fn": {
                "tagNames": {
                    "p-text": {
                        "amount": 4,
                        "hostPdsComponent": null,
                        "children": 4,
                        "properties": {
                            "tag": {
                                "amount": 4,
                                "values": {
                                    "p": 4
                                }
                            },
                            "size": {
                                "amount": 4,
                                "values": {
                                    "small": 4
                                }
                            },
                            "weight": {
                                "amount": 4,
                                "values": {
                                    "regular": 4
                                }
                            },
                            "align": {
                                "amount": 4,
                                "values": {
                                    "left": 4
                                }
                            },
                            "color": {
                                "amount": 4,
                                "values": {
                                    "default": 1,
                                    "inherit": 3
                                }
                            },
                            "ellipsis": {
                                "amount": 4,
                                "values": {
                                    "false": 4
                                }
                            },
                            "theme": {
                                "amount": 4,
                                "values": {
                                    "light": 4
                                }
                            }
                        },
                        "unusedProperties": []
                    },
                    "p-flex": {
                        "amount": 1,
                        "hostPdsComponent": null,
                        "children": 1,
                        "properties": {
                            "inline": {
                                "amount": 1,
                                "values": {
                                    "false": 1
                                }
                            },
                            "wrap": {
                                "amount": 1,
                                "values": {
                                    "nowrap": 1
                                }
                            },
                            "direction": {
                                "amount": 1,
                                "values": {
                                    "row": 1
                                }
                            },
                            "justifyContent": {
                                "amount": 1,
                                "values": {
                                    "flex-start": 1
                                }
                            },
                            "alignItems": {
                                "amount": 1,
                                "values": {
                                    "center": 1
                                }
                            },
                            "alignContent": {
                                "amount": 1,
                                "values": {
                                    "stretch": 1
                                }
                            }
                        },
                        "unusedProperties": []
                    },
                    "p-icon": {
                        "amount": 1,
                        "hostPdsComponent": null,
                        "children": null,
                        "properties": {
                            "name": {
                                "amount": 1,
                                "values": {
                                    "information": 1
                                }
                            },
                            "color": {
                                "amount": 1,
                                "values": {
                                    "inherit": 1
                                }
                            },
                            "size": {
                                "amount": 1,
                                "values": {
                                    "small": 1
                                }
                            },
                            "lazy": {
                                "amount": 1,
                                "values": {
                                    "false": 1
                                }
                            },
                            "theme": {
                                "amount": 1,
                                "values": {
                                    "light": 1
                                }
                            }
                        },
                        "unusedProperties": [
                            "source",
                            "aria"
                        ]
                    }
                },
                "unusedTagNames": [
                    "p-accordion",
                    "p-banner",
                    "p-button",
                    "p-button-group",
                    "p-button-pure",
                    "p-carousel",
                    "p-checkbox-wrapper",
                    "p-content-wrapper",
                    "p-divider",
                    "p-fieldset-wrapper",
                    "p-flex-item",
                    "p-grid",
                    "p-grid-item",
                    "p-headline",
                    "p-inline-notification",
                    "p-link",
                    "p-link-pure",
                    "p-link-social",
                    "p-link-tile",
                    "p-marque",
                    "p-modal",
                    "p-pagination",
                    "p-popover",
                    "p-radio-button-wrapper",
                    "p-scroller",
                    "p-segmented-control",
                    "p-segmented-control-item",
                    "p-select-wrapper",
                    "p-spinner",
                    "p-stepper-horizontal",
                    "p-stepper-horizontal-item",
                    "p-switch",
                    "p-table",
                    "p-table-body",
                    "p-table-cell",
                    "p-table-head",
                    "p-table-head-cell",
                    "p-table-head-row",
                    "p-table-row",
                    "p-tabs",
                    "p-tabs-bar",
                    "p-tabs-item",
                    "p-tag",
                    "p-tag-dismissible",
                    "p-text-field-wrapper",
                    "p-text-list",
                    "p-text-list-item",
                    "p-textarea-wrapper",
                    "p-toast"
                ]
            }
        }
    }
}